Workbook

Sheet Data
A1: InvoiceNumber | B1: Customer | C1: CustomerEmail | D1: InvoiceDate | E1: TermsDays | F1: DueDate | G1: Amount | H1: Status | I1: PaymentDate | J1: AmountPaid | K1: DaysToPay | L1: DaysLateAtPayment | M1: DaysPastDueNow | N1: Bucket | O1: OpenAmount | P1: OpenValueXAge
A2: INV-5001 | B2: Vantage Media Group | C2: ap@vantagemedia.group | D2: 45680 | E2: 30 | F2: 45710 | G2: 5050 | H2: Paid | I2: 45750 | J2: 5050 | K2: 70 | L2: 40 | M2: =IF($H2="Outstanding",MAX(0,Summary!$B$3-$F2),"") | N2: =IF($M2="","",IF($M2=0,"Current",IF($M2<=30,"1-30",IF($M2<=60,"31-60",IF($M2<=90,"61-90","90+"))))) | O2: =IF($H2="Outstanding",$G2,0) -> 0 | P2: =$O2*IF($M2="",0,$M2) -> 0
A3: INV-5002 | B3: Seoul Pharma Trading | C3: finance@seoulpharma.co | D3: 45660 | E3: 30 | F3: 45690 | G3: 8350 | H3: Paid | I3: 45716 | J3: 8350 | K3: 56 | L3: 26 | M3: =IF($H3="Outstanding",MAX(0,Summary!$B$3-$F3),"") | N3: =IF($M3="","",IF($M3=0,"Current",IF($M3<=30,"1-30",IF($M3<=60,"31-60",IF($M3<=90,"61-90","90+"))))) | O3: =IF($H3="Outstanding",$G3,0) -> 0 | P3: =$O3*IF($M3="",0,$M3) -> 0
A4: INV-5003 | B4: Northgate Property Mgmt | C4: vendors@northgatepm.com | D4: 45663 | E4: 30 | F4: 45693 | G4: 4100 | H4: Paid | I4: 45747 | J4: 4100 | K4: 84 | L4: 52 | M4: =IF($H4="Outstanding",MAX(0,Summary!$B$3-$F4),"") | N4: =IF($M4="","",IF($M4=0,"Current",IF($M4<=30,"1-30",IF($M4<=60,"31-60",IF($M4<=90,"61-90","90+"))))) | O4: =IF($H4="Outstanding",$G4,0) -> 0 | P4: =$O4*IF($M4="",0,$M4) -> 0
A5: INV-5004 | B5: Granite Civil Group | C5: ap@granitecivil.com | D5: 45673 | E5: 45 | F5: 45718 | G5: 34250 | H5: Paid | I5: 45755 | J5: 34250 | K5: 82 | L5: 37 | M5: =IF($H5="Outstanding",MAX(0,Summary!$B$3-$F5),"") | N5: =IF($M5="","",IF($M5=0,"Current",IF($M5<=30,"1-30",IF($M5<=60,"31-60",IF($M5<=90,"61-90","90+"))))) | O5: =IF($H5="Outstanding",$G5,0) -> 0 | P5: =$O5*IF($M5="",0,$M5) -> 0
A6: INV-5005 | B6: BlueRidge Hotels | C6: karen.wu@blueridgehotels.com | D6: 45667 | E6: 30 | F6: 45697 | G6: 14200 | H6: Paid | I6: 45709 | J6: 14200 | K6: 42 | L6: 12 | M6: =IF($H6="Outstanding",MAX(0,Summary!$B$3-$F6),"") | N6: =IF($M6="","",IF($M6=0,"Current",IF($M6<=30,"1-30",IF($M6<=60,"31-60",IF($M6<=90,"61-90","90+"))))) | O6: =IF($H6="Outstanding",$G6,0) -> 0 | P6: =$O6*IF($M6="",0,$M6) -> 0
A7: INV-5006 | B7: Stellar Staffing Co | C7: finance@stellarstaffing.co | D7: 45673 | E7: 15 | F7: 45688 | G7: 9150 | H7: Paid | I7: 45694 | J7: 9150 | K7: 21 | L7: 6 | M7: =IF($H7="Outstanding",MAX(0,Summary!$B$3-$F7),"") | N7: =IF($M7="","",IF($M7=0,"Current",IF($M7<=30,"1-30",IF($M7<=60,"31-60",IF($M7<=90,"61-90","90+"))))) | O7: =IF($H7="Outstanding",$G7,0) -> 0 | P7: =$O7*IF($M7="",0,$M7) -> 0
A8: INV-5007 | B8: BlueRidge Hotels | C8: karen.wu@blueridgehotels.com | D8: 45677 | E8: 30 | F8: 45707 | G8: 6900 | H8: Paid | I8: 45723 | J8: 6900 | K8: 46 | L8: 16 | M8: =IF($H8="Outstanding",MAX(0,Summary!$B$3-$F8),"") | N8: =IF($M8="","",IF($M8=0,"Current",IF($M8<=30,"1-30",IF($M8<=60,"31-60",IF($M8<=90,"61-90","90+"))))) | O8: =IF($H8="Outstanding",$G8,0) -> 0 | P8: =$O8*IF($M8="",0,$M8) -> 0
A9: INV-5008 | B9: Bluefin Seafood Dist | C9: payables@bluefindist.com | D9: 45681 | E9: 30 | F9: 45711 | G9: 8550 | H9: Paid | I9: 45737 | J9: 8550 | K9: 56 | L9: 26 | M9: =IF($H9="Outstanding",MAX(0,Summary!$B$3-$F9),"") | N9: =IF($M9="","",IF($M9=0,"Current",IF($M9<=30,"1-30",IF($M9<=60,"31-60",IF($M9<=90,"61-90","90+"))))) | O9: =IF($H9="Outstanding",$G9,0) -> 0 | P9: =$O9*IF($M9="",0,$M9) -> 0
A10: INV-5009 | B10: Ridgeline Builders | C10: ap@ridgelinebuilders.com | D10: 45660 | E10: 30 | F10: 45690 | G10: 10950 | H10: Paid | I10: 45726 | J10: 10950 | K10: 66 | L10: 36 | M10: =IF($H10="Outstanding",MAX(0,Summary!$B$3-$F10),"") | N10: =IF($M10="","",IF($M10=0,"Current",IF($M10<=30,"1-30",IF($M10<=60,"31-60",IF($M10<=90,"61-90","90+"))))) | O10: =IF($H10="Outstanding",$G10,0) -> 0 | P10: =$O10*IF($M10="",0,$M10) -> 0
A11: INV-5010 | B11: Foundry Dev Collective | C11: ops@foundrydev.co | D11: 45674 | E11: 30 | F11: 45704 | G11: 15700 | H11: Paid-Partial-then-Settled | I11: 45706 | J11: 15700 | K11: 32 | L11: 2 | M11: =IF($H11="Outstanding",MAX(0,Summary!$B$3-$F11),"") | N11: =IF($M11="","",IF($M11=0,"Current",IF($M11<=30,"1-30",IF($M11<=60,"31-60",IF($M11<=90,"61-90","90+"))))) | O11: =IF($H11="Outstanding",$G11,0) -> 0 | P11: =$O11*IF($M11="",0,$M11) -> 0
A12: INV-5011 | B12: Harborline Interiors | C12: kim@harborlineinteriors.com | D12: 45681 | E12: 15 | F12: 45696 | G12: 1900 | H12: Paid | I12: 45692 | J12: 1900 | K12: 11 | L12: -4 | M12: =IF($H12="Outstanding",MAX(0,Summary!$B$3-$F12),"") | N12: =IF($M12="","",IF($M12=0,"Current",IF($M12<=30,"1-30",IF($M12<=60,"31-60",IF($M12<=90,"61-90","90+"))))) | O12: =IF($H12="Outstanding",$G12,0) -> 0 | P12: =$O12*IF($M12="",0,$M12) -> 0
A13: INV-5012 | B13: Seoul Pharma Trading | C13: finance@seoulpharma.co | D13: 45673 | E13: 30 | F13: 45703 | G13: 18000 | H13: Paid | I13: 45715 | J13: 18000 | K13: 42 | L13: 12 | M13: =IF($H13="Outstanding",MAX(0,Summary!$B$3-$F13),"") | N13: =IF($M13="","",IF($M13=0,"Current",IF($M13<=30,"1-30",IF($M13<=60,"31-60",IF($M13<=90,"61-90","90+"))))) | O13: =IF($H13="Outstanding",$G13,0) -> 0 | P13: =$O13*IF($M13="",0,$M13) -> 0
... A167: INV-5166 | B167: Seoul Pharma Trading | C167: finance@seoulpharma.co | D167: 46057 | E167: 30 | F167: 46087 | G167: 7200 | H167: Paid | I167: 46125 | J167: 7200 | K167: 68 | L167: 38 | M167: =IF($H167="Outstanding",MAX(0,Summary!$B$3-$F167),"") | N167: =IF($M167="","",IF($M167=0,"Current",IF($M167<=30,"1-30",IF($M167<=60,"31-60",IF($M167<=90,"61-90","90+"))))) | O167: =IF($H167="Outstanding",$G167,0) -> 0 | P167: =$O167*IF($M167="",0,$M167) -> 0
A168: INV-5167 | B168: Northgate Property Mgmt | C168: vendors@northgatepm.com | D168: 46062 | E168: 30 | F168: 46092 | G168: 2300 | H168: Outstanding | J168: 0 | M168: =IF($H168="Outstanding",MAX(0,Summary!$B$3-$F168),"") -> 133 | N168: =IF($M168="","",IF($M168=0,"Current",IF($M168<=30,"1-30",IF($M168<=60,"31-60",IF($M168<=90,"61-90","90+"))))) -> 90+ | O168: =IF($H168="Outstanding",$G168,0) -> 2300 | P168: =$O168*IF($M168="",0,$M168) -> 305900
A169: INV-5168 | B169: TrueNorth MSP | C169: billing@truenorthmsp.com | D169: 46056 | E169: 15 | F169: 46071 | G169: 4200 | H169: Paid | I169: 46076 | J169: 4200 | K169: 20 | L169: 4 | M169: =IF($H169="Outstanding",MAX(0,Summary!$B$3-$F169),"") | N169: =IF($M169="","",IF($M169=0,"Current",IF($M169<=30,"1-30",IF($M169<=60,"31-60",IF($M169<=90,"61-90","90+"))))) | O169: =IF($H169="Outstanding",$G169,0) -> 0 | P169: =$O169*IF($M169="",0,$M169) -> 0
A170: INV-5169 | B170: Ridgeline Builders | C170: ap@ridgelinebuilders.com | D170: 46078 | E170: 30 | F170: 46108 | G170: 17300 | H170: Outstanding | J170: 0 | M170: =IF($H170="Outstanding",MAX(0,Summary!$B$3-$F170),"") -> 117 | N170: =IF($M170="","",IF($M170=0,"Current",IF($M170<=30,"1-30",IF($M170<=60,"31-60",IF($M170<=90,"61-90","90+"))))) -> 90+ | O170: =IF($H170="Outstanding",$G170,0) -> 17300 | P170: =$O170*IF($M170="",0,$M170) -> 2024100
A171: INV-5170 | B171: Bluefin Seafood Dist | C171: payables@bluefindist.com | D171: 46072 | E171: 30 | F171: 46102 | G171: 5250 | H171: Paid | I171: 46125 | J171: 5250 | K171: 53 | L171: 21 | M171: =IF($H171="Outstanding",MAX(0,Summary!$B$3-$F171),"") | N171: =IF($M171="","",IF($M171=0,"Current",IF($M171<=30,"1-30",IF($M171<=60,"31-60",IF($M171<=90,"61-90","90+"))))) | O171: =IF($H171="Outstanding",$G171,0) -> 0 | P171: =$O171*IF($M171="",0,$M171) -> 0
A172: INV-5171 | B172: Orchid Labs | C172: finance@orchidlabs.io | D172: 46072 | E172: 30 | F172: 46102 | G172: 9150 | H172: Paid | I172: 46113 | J172: 9150 | K172: 41 | L172: 11 | M172: =IF($H172="Outstanding",MAX(0,Summary!$B$3-$F172),"") | N172: =IF($M172="","",IF($M172=0,"Current",IF($M172<=30,"1-30",IF($M172<=60,"31-60",IF($M172<=90,"61-90","90+"))))) | O172: =IF($H172="Outstanding",$G172,0) -> 0 | P172: =$O172*IF($M172="",0,$M172) -> 0
A173: INV-5172 | B173: BlueRidge Hotels | C173: karen.wu@blueridgehotels.com | D173: 46076 | E173: 30 | F173: 46106 | G173: 10300 | H173: Paid | I173: 46121 | J173: 10300 | K173: 45 | L173: 15 | M173: =IF($H173="Outstanding",MAX(0,Summary!$B$3-$F173),"") | N173: =IF($M173="","",IF($M173=0,"Current",IF($M173<=30,"1-30",IF($M173<=60,"31-60",IF($M173<=90,"61-90","90+"))))) | O173: =IF($H173="Outstanding",$G173,0) -> 0 | P173: =$O173*IF($M173="",0,$M173) -> 0
A174: INV-5173 | B174: Seoul Pharma Trading | C174: finance@seoulpharma.co | D174: 46069 | E174: 30 | F174: 46099 | G174: 6000 | H174: Paid | I174: 46134 | J174: 6000 | K174: 65 | L174: 35 | M174: =IF($H174="Outstanding",MAX(0,Summary!$B$3-$F174),"") | N174: =IF($M174="","",IF($M174=0,"Current",IF($M174<=30,"1-30",IF($M174<=60,"31-60",IF($M174<=90,"61-90","90+"))))) | O174: =IF($H174="Outstanding",$G174,0) -> 0 | P174: =$O174*IF($M174="",0,$M174) -> 0
A175: INV-5174 | B175: Harborline Interiors | C175: kim@harborlineinteriors.com | D175: 46062 | E175: 15 | F175: 46077 | G175: 3000 | H175: Paid | I175: 46079 | J175: 3000 | K175: 17 | L175: 2 | M175: =IF($H175="Outstanding",MAX(0,Summary!$B$3-$F175),"") | N175: =IF($M175="","",IF($M175=0,"Current",IF($M175<=30,"1-30",IF($M175<=60,"31-60",IF($M175<=90,"61-90","90+"))))) | O175: =IF($H175="Outstanding",$G175,0) -> 0 | P175: =$O175*IF($M175="",0,$M175) -> 0
A176: INV-5175 | B176: Quarry & Co Wholesale | C176: ap@quarryco.com | D176: 46065 | E176: 30 | F176: 46095 | G176: 7300 | H176: Paid | I176: 46118 | J176: 7300 | K176: 53 | L176: 21 | M176: =IF($H176="Outstanding",MAX(0,Summary!$B$3-$F176),"") | N176: =IF($M176="","",IF($M176=0,"Current",IF($M176<=30,"1-30",IF($M176<=60,"31-60",IF($M176<=90,"61-90","90+"))))) | O176: =IF($H176="Outstanding",$G176,0) -> 0 | P176: =$O176*IF($M176="",0,$M176) -> 0
A177: INV-5176 | B177: Lakeshore Events | C177: accounts@lakeshoreevents.com | D177: 46055 | E177: 30 | F177: 46085 | G177: 6800 | H177: Paid | I177: 46118 | J177: 6800 | K177: 63 | L177: 32 | M177: =IF($H177="Outstanding",MAX(0,Summary!$B$3-$F177),"") | N177: =IF($M177="","",IF($M177=0,"Current",IF($M177<=30,"1-30",IF($M177<=60,"31-60",IF($M177<=90,"61-90","90+"))))) | O177: =IF($H177="Outstanding",$G177,0) -> 0 | P177: =$O177*IF($M177="",0,$M177) -> 0
A178: INV-5177 | B178: Cascade Logistics | C178: payables@cascadelogistics.com | D178: 46091 | E178: 30 | F178: 46121 | G178: 10300 | H178: Paid | I178: 46136 | J178: 10300 | K178: 45 | L178: 15 | M178: =IF($H178="Outstanding",MAX(0,Summary!$B$3-$F178),"") | N178: =IF($M178="","",IF($M178=0,"Current",IF($M178<=30,"1-30",IF($M178<=60,"31-60",IF($M178<=90,"61-90","90+"))))) | O178: =IF($H178="Outstanding",$G178,0) -> 0 | P178: =$O178*IF($M178="",0,$M178) -> 0
A179: INV-5178 | B179: Quarry & Co Wholesale | C179: ap@quarryco.com | D179: 46101 | E179: 30 | F179: 46131 | G179: 8150 | H179: Paid | I179: 46146 | J179: 8150 | K179: 45 | L179: 15 | M179: =IF($H179="Outstanding",MAX(0,Summary!$B$3-$F179),"") | N179: =IF($M179="","",IF($M179=0,"Current",IF($M179<=30,"1-30",IF($M179<=60,"31-60",IF($M179<=90,"61-90","90+"))))) | O179: =IF($H179="Outstanding",$G179,0) -> 0 | P179: =$O179*IF($M179="",0,$M179) -> 0
A180: INV-5179 | B180: Granite Civil Group | C180: ap@granitecivil.com | D180: 46094 | E180: 45 | F180: 46139 | G180: 22050 | H180: Outstanding | J180: 0 | M180: =IF($H180="Outstanding",MAX(0,Summary!$B$3-$F180),"") -> 86 | N180: =IF($M180="","",IF($M180=0,"Current",IF($M180<=30,"1-30",IF($M180<=60,"31-60",IF($M180<=90,"61-90","90+"))))) -> 61-90 | O180: =IF($H180="Outstanding",$G180,0) -> 22050 | P180: =$O180*IF($M180="",0,$M180) -> 1896300
A181: INV-5180 | B181: Apex Mechanical | C181: accounts@apexmech.com | D181: 46083 | E181: 30 | F181: 46113 | G181: 4850 | H181: Paid | I181: 46115 | J181: 4850 | K181: 32 | L181: 2 | M181: =IF($H181="Outstanding",MAX(0,Summary!$B$3-$F181),"") | N181: =IF($M181="","",IF($M181=0,"Current",IF($M181<=30,"1-30",IF($M181<=60,"31-60",IF($M181<=90,"61-90","90+"))))) | O181: =IF($H181="Outstanding",$G181,0) -> 0 | P181: =$O181*IF($M181="",0,$M181) -> 0
A182: INV-5181 | B182: Meridian Health Partners | C182: billing@meridianhp.com | D182: 46100 | E182: 30 | F182: 46130 | G182: 10150 | H182: Paid | I182: 46153 | J182: 10150 | K182: 53 | L182: 23 | M182: =IF($H182="Outstanding",MAX(0,Summary!$B$3-$F182),"") | N182: =IF($M182="","",IF($M182=0,"Current",IF($M182<=30,"1-30",IF($M182<=60,"31-60",IF($M182<=90,"61-90","90+"))))) | O182: =IF($H182="Outstanding",$G182,0) -> 0 | P182: =$O182*IF($M182="",0,$M182) -> 0
A183: INV-5182 | B183: Ridgeline Builders | C183: ap@ridgelinebuilders.com | D183: 46086 | E183: 30 | F183: 46116 | G183: 23250 | H183: Outstanding | J183: 0 | M183: =IF($H183="Outstanding",MAX(0,Summary!$B$3-$F183),"") -> 109 | N183: =IF($M183="","",IF($M183=0,"Current",IF($M183<=30,"1-30",IF($M183<=60,"31-60",IF($M183<=90,"61-90","90+"))))) -> 90+ | O183: =IF($H183="Outstanding",$G183,0) -> 23250 | P183: =$O183*IF($M183="",0,$M183) -> 2534250
A184: INV-5183 | B184: TrueNorth MSP | C184: billing@truenorthmsp.com | D184: 46097 | E184: 15 | F184: 46112 | G184: 3800 | H184: Paid | I184: 46115 | J184: 3800 | K184: 18 | L184: 3 | M184: =IF($H184="Outstanding",MAX(0,Summary!$B$3-$F184),"") | N184: =IF($M184="","",IF($M184=0,"Current",IF($M184<=30,"1-30",IF($M184<=60,"31-60",IF($M184<=90,"61-90","90+"))))) | O184: =IF($H184="Outstanding",$G184,0) -> 0 | P184: =$O184*IF($M184="",0,$M184) -> 0
A185: INV-5184 | B185: Harborline Interiors | C185: kim@harborlineinteriors.com | D185: 46104 | E185: 15 | F185: 46119 | G185: 1100 | H185: Paid | I185: 46119 | J185: 1100 | K185: 15 | L185: 0 | M185: =IF($H185="Outstanding",MAX(0,Summary!$B$3-$F185),"") | N185: =IF($M185="","",IF($M185=0,"Current",IF($M185<=30,"1-30",IF($M185<=60,"31-60",IF($M185<=90,"61-90","90+"))))) | O185: =IF($H185="Outstanding",$G185,0) -> 0 | P185: =$O185*IF($M185="",0,$M185) -> 0
A186: INV-5185 | B186: Seoul Pharma Trading | C186: finance@seoulpharma.co | D186: 46104 | E186: 30 | F186: 46134 | G186: 7600 | H186: Paid | I186: 46178 | J186: 7600 | K186: 74 | L186: 44 | M186: =IF($H186="Outstanding",MAX(0,Summary!$B$3-$F186),"") | N186: =IF($M186="","",IF($M186=0,"Current",IF($M186<=30,"1-30",IF($M186<=60,"31-60",IF($M186<=90,"61-90","90+"))))) | O186: =IF($H186="Outstanding",$G186,0) -> 0 | P186: =$O186*IF($M186="",0,$M186) -> 0
A187: INV-5186 | B187: Stellar Staffing Co | C187: finance@stellarstaffing.co | D187: 46097 | E187: 15 | F187: 46112 | G187: 13900 | H187: Paid | I187: 46118 | J187: 13900 | K187: 21 | L187: 5 | M187: =IF($H187="Outstanding",MAX(0,Summary!$B$3-$F187),"") | N187: =IF($M187="","",IF($M187=0,"Current",IF($M187<=30,"1-30",IF($M187<=60,"31-60",IF($M187<=90,"61-90","90+"))))) | O187: =IF($H187="Outstanding",$G187,0) -> 0 | P187: =$O187*IF($M187="",0,$M187) -> 0
A188: INV-5187 | B188: Vantage Media Group | C188: ap@vantagemedia.group | D188: 46101 | E188: 30 | F188: 46131 | G188: 5050 | H188: Outstanding | J188: 0 | M188: =IF($H188="Outstanding",MAX(0,Summary!$B$3-$F188),"") -> 94 | N188: =IF($M188="","",IF($M188=0,"Current",IF($M188<=30,"1-30",IF($M188<=60,"31-60",IF($M188<=90,"61-90","90+"))))) -> 90+ | O188: =IF($H188="Outstanding",$G188,0) -> 5050 | P188: =$O188*IF($M188="",0,$M188) -> 474700
A189: INV-5188 | B189: Bluefin Seafood Dist | C189: payables@bluefindist.com | D189: 46097 | E189: 30 | F189: 46127 | G189: 7750 | H189: Paid | I189: 46149 | J189: 7750 | K189: 52 | L189: 22 | M189: =IF($H189="Outstanding",MAX(0,Summary!$B$3-$F189),"") | N189: =IF($M189="","",IF($M189=0,"Current",IF($M189<=30,"1-30",IF($M189<=60,"31-60",IF($M189<=90,"61-90","90+"))))) | O189: =IF($H189="Outstanding",$G189,0) -> 0 | P189: =$O189*IF($M189="",0,$M189) -> 0
A190: INV-5189 | B190: Seoul Pharma Trading | C190: finance@seoulpharma.co | D190: 46104 | E190: 30 | F190: 46134 | G190: 13950 | H190: Paid | I190: 46181 | J190: 13950 | K190: 77 | L190: 47 | M190: =IF($H190="Outstanding",MAX(0,Summary!$B$3-$F190),"") | N190: =IF($M190="","",IF($M190=0,"Current",IF($M190<=30,"1-30",IF($M190<=60,"31-60",IF($M190<=90,"61-90","90+"))))) | O190: =IF($H190="Outstanding",$G190,0) -> 0 | P190: =$O190*IF($M190="",0,$M190) -> 0
A191: INV-5190 | B191: Cascade Logistics | C191: payables@cascadelogistics.com | D191: 46084 | E191: 30 | F191: 46114 | G191: 17900 | H191: Paid | I191: 46118 | J191: 17900 | K191: 34 | L191: 4 | M191: =IF($H191="Outstanding",MAX(0,Summary!$B$3-$F191),"") | N191: =IF($M191="","",IF($M191=0,"Current",IF($M191<=30,"1-30",IF($M191<=60,"31-60",IF($M191<=90,"61-90","90+"))))) | O191: =IF($H191="Outstanding",$G191,0) -> 0 | P191: =$O191*IF($M191="",0,$M191) -> 0
A192: INV-5191 | B192: Ridgeline Builders | C192: ap@ridgelinebuilders.com | D192: 46099 | E192: 30 | F192: 46129 | G192: 18200 | H192: Outstanding | J192: 0 | M192: =IF($H192="Outstanding",MAX(0,Summary!$B$3-$F192),"") -> 96 | N192: =IF($M192="","",IF($M192=0,"Current",IF($M192<=30,"1-30",IF($M192<=60,"31-60",IF($M192<=90,"61-90","90+"))))) -> 90+ | O192: =IF($H192="Outstanding",$G192,0) -> 18200 | P192: =$O192*IF($M192="",0,$M192) -> 1747200
A193: INV-5192 | B193: Foundry Dev Collective | C193: ops@foundrydev.co | D193: 46104 | E193: 30 | F193: 46134 | G193: 33100 | H193: Paid | I193: 46160 | J193: 33100 | K193: 56 | L193: 26 | M193: =IF($H193="Outstanding",MAX(0,Summary!$B$3-$F193),"") | N193: =IF($M193="","",IF($M193=0,"Current",IF($M193<=30,"1-30",IF($M193<=60,"31-60",IF($M193<=90,"61-90","90+"))))) | O193: =IF($H193="Outstanding",$G193,0) -> 0 | P193: =$O193*IF($M193="",0,$M193) -> 0
A194: INV-5193 | B194: Apex Mechanical | C194: accounts@apexmech.com | D194: 46086 | E194: 30 | F194: 46116 | G194: 4000 | H194: Paid | I194: 46118 | J194: 4000 | K194: 32 | L194: 2 | M194: =IF($H194="Outstanding",MAX(0,Summary!$B$3-$F194),"") | N194: =IF($M194="","",IF($M194=0,"Current",IF($M194<=30,"1-30",IF($M194<=60,"31-60",IF($M194<=90,"61-90","90+"))))) | O194: =IF($H194="Outstanding",$G194,0) -> 0 | P194: =$O194*IF($M194="",0,$M194) -> 0
A195: INV-5194 | B195: Quarry & Co Wholesale | C195: ap@quarryco.com | D195: 46093 | E195: 30 | F195: 46123 | G195: 5450 | H195: Paid | I195: 46146 | J195: 5450 | K195: 53 | L195: 22 | M195: =IF($H195="Outstanding",MAX(0,Summary!$B$3-$F195),"") | N195: =IF($M195="","",IF($M195=0,"Current",IF($M195<=30,"1-30",IF($M195<=60,"31-60",IF($M195<=90,"61-90","90+"))))) | O195: =IF($H195="Outstanding",$G195,0) -> 0 | P195: =$O195*IF($M195="",0,$M195) -> 0
A196: INV-5195 | B196: Northgate Property Mgmt | C196: vendors@northgatepm.com | D196: 46104 | E196: 30 | F196: 46134 | G196: 5600 | H196: Paid | I196: 46171 | J196: 5600 | K196: 67 | L196: 37 | M196: =IF($H196="Outstanding",MAX(0,Summary!$B$3-$F196),"") | N196: =IF($M196="","",IF($M196=0,"Current",IF($M196<=30,"1-30",IF($M196<=60,"31-60",IF($M196<=90,"61-90","90+"))))) | O196: =IF($H196="Outstanding",$G196,0) -> 0 | P196: =$O196*IF($M196="",0,$M196) -> 0
A197: INV-5196 | B197: TrueNorth MSP | C197: billing@truenorthmsp.com | D197: 46115 | E197: 15 | F197: 46130 | G197: 4950 | H197: Paid | I197: 46133 | J197: 4950 | K197: 18 | L197: 3 | M197: =IF($H197="Outstanding",MAX(0,Summary!$B$3-$F197),"") | N197: =IF($M197="","",IF($M197=0,"Current",IF($M197<=30,"1-30",IF($M197<=60,"31-60",IF($M197<=90,"61-90","90+"))))) | O197: =IF($H197="Outstanding",$G197,0) -> 0 | P197: =$O197*IF($M197="",0,$M197) -> 0
A198: INV-5197 | B198: Seoul Pharma Trading | C198: finance@seoulpharma.co | D198: 46125 | E198: 30 | F198: 46155 | G198: 14650 | H198: Paid | I198: 46197 | J198: 14650 | K198: 72 | L198: 42 | M198: =IF($H198="Outstanding",MAX(0,Summary!$B$3-$F198),"") | N198: =IF($M198="","",IF($M198=0,"Current",IF($M198<=30,"1-30",IF($M198<=60,"31-60",IF($M198<=90,"61-90","90+"))))) | O198: =IF($H198="Outstanding",$G198,0) -> 0 | P198: =$O198*IF($M198="",0,$M198) -> 0
A199: INV-5198 | B199: Seoul Pharma Trading | C199: finance@seoulpharma.co | D199: 46135 | E199: 30 | F199: 46165 | G199: 17450 | H199: Paid | I199: 46216 | J199: 17450 | K199: 81 | L199: 49 | M199: =IF($H199="Outstanding",MAX(0,Summary!$B$3-$F199),"") | N199: =IF($M199="","",IF($M199=0,"Current",IF($M199<=30,"1-30",IF($M199<=60,"31-60",IF($M199<=90,"61-90","90+"))))) | O199: =IF($H199="Outstanding",$G199,0) -> 0 | P199: =$O199*IF($M199="",0,$M199) -> 0
A200: INV-5199 | B200: Harborline Interiors | C200: kim@harborlineinteriors.com | D200: 46136 | E200: 15 | F200: 46151 | G200: 4500 | H200: Paid | I200: 46153 | J200: 4500 | K200: 17 | L200: 2 | M200: =IF($H200="Outstanding",MAX(0,Summary!$B$3-$F200),"") | N200: =IF($M200="","",IF($M200=0,"Current",IF($M200<=30,"1-30",IF($M200<=60,"31-60",IF($M200<=90,"61-90","90+"))))) | O200: =IF($H200="Outstanding",$G200,0) -> 0 | P200: =$O200*IF($M200="",0,$M200) -> 0
A201: INV-5200 | B201: Meridian Health Partners | C201: billing@meridianhp.com | D201: 46134 | E201: 30 | F201: 46164 | G201: 7650 | H201: Paid | I201: 46189 | J201: 7650 | K201: 55 | L201: 25 | M201: =IF($H201="Outstanding",MAX(0,Summary!$B$3-$F201),"") | N201: =IF($M201="","",IF($M201=0,"Current",IF($M201<=30,"1-30",IF($M201<=60,"31-60",IF($M201<=90,"61-90","90+"))))) | O201: =IF($H201="Outstanding",$G201,0) -> 0 | P201: =$O201*IF($M201="",0,$M201) -> 0
A202: INV-5201 | B202: Ridgeline Builders | C202: ap@ridgelinebuilders.com | D202: 46125 | E202: 30 | F202: 46155 | G202: 6350 | H202: Paid | I202: 46189 | J202: 6350 | K202: 64 | L202: 34 | M202: =IF($H202="Outstanding",MAX(0,Summary!$B$3-$F202),"") | N202: =IF($M202="","",IF($M202=0,"Current",IF($M202<=30,"1-30",IF($M202<=60,"31-60",IF($M202<=90,"61-90","90+"))))) | O202: =IF($H202="Outstanding",$G202,0) -> 0 | P202: =$O202*IF($M202="",0,$M202) -> 0
A203: INV-5202 | B203: Orchid Labs | C203: finance@orchidlabs.io | D203: 46125 | E203: 30 | F203: 46155 | G203: 11600 | H203: Paid | I203: 46174 | J203: 11600 | K203: 49 | L203: 17 | M203: =IF($H203="Outstanding",MAX(0,Summary!$B$3-$F203),"") | N203: =IF($M203="","",IF($M203=0,"Current",IF($M203<=30,"1-30",IF($M203<=60,"31-60",IF($M203<=90,"61-90","90+"))))) | O203: =IF($H203="Outstanding",$G203,0) -> 0 | P203: =$O203*IF($M203="",0,$M203) -> 0
A204: INV-5203 | B204: Pinewood Consulting | C204: amara@pinewoodconsulting.com | D204: 46128 | E204: 15 | F204: 46143 | G204: 2350 | H204: Paid | I204: 46146 | J204: 2350 | K204: 18 | L204: 2 | M204: =IF($H204="Outstanding",MAX(0,Summary!$B$3-$F204),"") | N204: =IF($M204="","",IF($M204=0,"Current",IF($M204<=30,"1-30",IF($M204<=60,"31-60",IF($M204<=90,"61-90","90+"))))) | O204: =IF($H204="Outstanding",$G204,0) -> 0 | P204: =$O204*IF($M204="",0,$M204) -> 0
... A209: INV-5208 | B209: Foundry Dev Collective | C209: ops@foundrydev.co | D209: 46118 | E209: 30 | F209: 46148 | G209: 13050 | H209: Paid | I209: 46153 | J209: 13050 | K209: 35 | L209: 3 | M209: =IF($H209="Outstanding",MAX(0,Summary!$B$3-$F209),"") | N209: =IF($M209="","",IF($M209=0,"Current",IF($M209<=30,"1-30",IF($M209<=60,"31-60",IF($M209<=90,"61-90","90+"))))) | O209: =IF($H209="Outstanding",$G209,0) -> 0 | P209: =$O209*IF($M209="",0,$M209) -> 0
A210: INV-5209 | B210: Granite Civil Group | C210: ap@granitecivil.com | D210: 46167 | E210: 45 | F210: 46212 | G210: 26250 | H210: Outstanding | J210: 0 | M210: =IF($H210="Outstanding",MAX(0,Summary!$B$3-$F210),"") -> 13 | N210: =IF($M210="","",IF($M210=0,"Current",IF($M210<=30,"1-30",IF($M210<=60,"31-60",IF($M210<=90,"61-90","90+"))))) -> 1-30 | O210: =IF($H210="Outstanding",$G210,0) -> 26250 | P210: =$O210*IF($M210="",0,$M210) -> 341250
A211: INV-5210 | B211: BlueRidge Hotels | C211: karen.wu@blueridgehotels.com | D211: 46146 | E211: 30 | F211: 46176 | G211: 12200 | H211: Paid | I211: 46188 | J211: 12200 | K211: 42 | L211: 12 | M211: =IF($H211="Outstanding",MAX(0,Summary!$B$3-$F211),"") | N211: =IF($M211="","",IF($M211=0,"Current",IF($M211<=30,"1-30",IF($M211<=60,"31-60",IF($M211<=90,"61-90","90+"))))) | O211: =IF($H211="Outstanding",$G211,0) -> 0 | P211: =$O211*IF($M211="",0,$M211) -> 0
A212: INV-5211 | B212: Ridgeline Builders | C212: ap@ridgelinebuilders.com | D212: 46164 | E212: 30 | F212: 46194 | G212: 18950 | H212: Outstanding | J212: 0 | M212: =IF($H212="Outstanding",MAX(0,Summary!$B$3-$F212),"") -> 31 | N212: =IF($M212="","",IF($M212=0,"Current",IF($M212<=30,"1-30",IF($M212<=60,"31-60",IF($M212<=90,"61-90","90+"))))) -> 31-60 | O212: =IF($H212="Outstanding",$G212,0) -> 18950 | P212: =$O212*IF($M212="",0,$M212) -> 587450
A213: INV-5212 | B213: BlueRidge Hotels | C213: karen.wu@blueridgehotels.com | D213: 46167 | E213: 30 | F213: 46197 | G213: 18950 | H213: Paid | I213: 46212 | J213: 18950 | K213: 45 | L213: 15 | M213: =IF($H213="Outstanding",MAX(0,Summary!$B$3-$F213),"") | N213: =IF($M213="","",IF($M213=0,"Current",IF($M213<=30,"1-30",IF($M213<=60,"31-60",IF($M213<=90,"61-90","90+"))))) | O213: =IF($H213="Outstanding",$G213,0) -> 0 | P213: =$O213*IF($M213="",0,$M213) -> 0
A214: INV-5213 | B214: TrueNorth MSP | C214: billing@truenorthmsp.com | D214: 46157 | E214: 15 | F214: 46172 | G214: 4500 | H214: Paid | I214: 46174 | J214: 4500 | K214: 17 | L214: 2 | M214: =IF($H214="Outstanding",MAX(0,Summary!$B$3-$F214),"") | N214: =IF($M214="","",IF($M214=0,"Current",IF($M214<=30,"1-30",IF($M214<=60,"31-60",IF($M214<=90,"61-90","90+"))))) | O214: =IF($H214="Outstanding",$G214,0) -> 0 | P214: =$O214*IF($M214="",0,$M214) -> 0
A215: INV-5214 | B215: Seoul Pharma Trading | C215: finance@seoulpharma.co | D215: 46160 | E215: 30 | F215: 46190 | G215: 18550 | H215: Outstanding | J215: 0 | M215: =IF($H215="Outstanding",MAX(0,Summary!$B$3-$F215),"") -> 35 | N215: =IF($M215="","",IF($M215=0,"Current",IF($M215<=30,"1-30",IF($M215<=60,"31-60",IF($M215<=90,"61-90","90+"))))) -> 31-60 | O215: =IF($H215="Outstanding",$G215,0) -> 18550 | P215: =$O215*IF($M215="",0,$M215) -> 649250
A216: INV-5215 | B216: Apex Mechanical | C216: accounts@apexmech.com | D216: 46149 | E216: 30 | F216: 46179 | G216: 4250 | H216: Paid | I216: 46191 | J216: 4250 | K216: 42 | L216: 12 | M216: =IF($H216="Outstanding",MAX(0,Summary!$B$3-$F216),"") | N216: =IF($M216="","",IF($M216=0,"Current",IF($M216<=30,"1-30",IF($M216<=60,"31-60",IF($M216<=90,"61-90","90+"))))) | O216: =IF($H216="Outstanding",$G216,0) -> 0 | P216: =$O216*IF($M216="",0,$M216) -> 0
A217: INV-5216 | B217: Cascade Logistics | C217: payables@cascadelogistics.com | D217: 46157 | E217: 30 | F217: 46187 | G217: 31100 | H217: Paid | I217: 46195 | J217: 31100 | K217: 38 | L217: 6 | M217: =IF($H217="Outstanding",MAX(0,Summary!$B$3-$F217),"") | N217: =IF($M217="","",IF($M217=0,"Current",IF($M217<=30,"1-30",IF($M217<=60,"31-60",IF($M217<=90,"61-90","90+"))))) | O217: =IF($H217="Outstanding",$G217,0) -> 0 | P217: =$O217*IF($M217="",0,$M217) -> 0
A218: INV-5217 | B218: Meridian Health Partners | C218: billing@meridianhp.com | D218: 46167 | E218: 30 | F218: 46197 | G218: 7200 | H218: Paid | I218: 46216 | J218: 7200 | K218: 49 | L218: 19 | M218: =IF($H218="Outstanding",MAX(0,Summary!$B$3-$F218),"") | N218: =IF($M218="","",IF($M218=0,"Current",IF($M218<=30,"1-30",IF($M218<=60,"31-60",IF($M218<=90,"61-90","90+"))))) | O218: =IF($H218="Outstanding",$G218,0) -> 0 | P218: =$O218*IF($M218="",0,$M218) -> 0
A219: INV-5218 | B219: Northgate Property Mgmt | C219: vendors@northgatepm.com | D219: 46149 | E219: 30 | F219: 46179 | G219: 6250 | H219: Paid | I219: 46220 | J219: 6250 | K219: 71 | L219: 41 | M219: =IF($H219="Outstanding",MAX(0,Summary!$B$3-$F219),"") | N219: =IF($M219="","",IF($M219=0,"Current",IF($M219<=30,"1-30",IF($M219<=60,"31-60",IF($M219<=90,"61-90","90+"))))) | O219: =IF($H219="Outstanding",$G219,0) -> 0 | P219: =$O219*IF($M219="",0,$M219) -> 0
A220: INV-5219 | B220: Stellar Staffing Co | C220: finance@stellarstaffing.co | D220: 46147 | E220: 15 | F220: 46162 | G220: 19850 | H220: Paid | I220: 46167 | J220: 19850 | K220: 20 | L220: 5 | M220: =IF($H220="Outstanding",MAX(0,Summary!$B$3-$F220),"") | N220: =IF($M220="","",IF($M220=0,"Current",IF($M220<=30,"1-30",IF($M220<=60,"31-60",IF($M220<=90,"61-90","90+"))))) | O220: =IF($H220="Outstanding",$G220,0) -> 0 | P220: =$O220*IF($M220="",0,$M220) -> 0
A221: INV-5220 | B221: Lakeshore Events | C221: accounts@lakeshoreevents.com | D221: 46154 | E221: 30 | F221: 46184 | G221: 9200 | H221: Paid | I221: 46209 | J221: 9200 | K221: 55 | L221: 23 | M221: =IF($H221="Outstanding",MAX(0,Summary!$B$3-$F221),"") | N221: =IF($M221="","",IF($M221=0,"Current",IF($M221<=30,"1-30",IF($M221<=60,"31-60",IF($M221<=90,"61-90","90+"))))) | O221: =IF($H221="Outstanding",$G221,0) -> 0 | P221: =$O221*IF($M221="",0,$M221) -> 0
A222: INV-5221 | B222: Foundry Dev Collective | C222: ops@foundrydev.co | D222: 46146 | E222: 30 | F222: 46176 | G222: 26800 | H222: Paid-Partial-then-Settled | I222: 46183 | J222: 26800 | K222: 37 | L222: 7 | M222: =IF($H222="Outstanding",MAX(0,Summary!$B$3-$F222),"") | N222: =IF($M222="","",IF($M222=0,"Current",IF($M222<=30,"1-30",IF($M222<=60,"31-60",IF($M222<=90,"61-90","90+"))))) | O222: =IF($H222="Outstanding",$G222,0) -> 0 | P222: =$O222*IF($M222="",0,$M222) -> 0
A223: INV-5222 | B223: Orchid Labs | C223: finance@orchidlabs.io | D223: 46148 | E223: 30 | F223: 46178 | G223: 6200 | H223: Paid | I223: 46185 | J223: 6200 | K223: 37 | L223: 7 | M223: =IF($H223="Outstanding",MAX(0,Summary!$B$3-$F223),"") | N223: =IF($M223="","",IF($M223=0,"Current",IF($M223<=30,"1-30",IF($M223<=60,"31-60",IF($M223<=90,"61-90","90+"))))) | O223: =IF($H223="Outstanding",$G223,0) -> 0 | P223: =$O223*IF($M223="",0,$M223) -> 0
A224: INV-5223 | B224: Apex Mechanical | C224: accounts@apexmech.com | D224: 46160 | E224: 30 | F224: 46190 | G224: 2600 | H224: Paid | I224: 46188 | J224: 2600 | K224: 28 | L224: -2 | M224: =IF($H224="Outstanding",MAX(0,Summary!$B$3-$F224),"") | N224: =IF($M224="","",IF($M224=0,"Current",IF($M224<=30,"1-30",IF($M224<=60,"31-60",IF($M224<=90,"61-90","90+"))))) | O224: =IF($H224="Outstanding",$G224,0) -> 0 | P224: =$O224*IF($M224="",0,$M224) -> 0
A225: INV-5224 | B225: Foundry Dev Collective | C225: ops@foundrydev.co | D225: 46181 | E225: 30 | F225: 46211 | G225: 29400 | H225: Outstanding | J225: 0 | M225: =IF($H225="Outstanding",MAX(0,Summary!$B$3-$F225),"") -> 14 | N225: =IF($M225="","",IF($M225=0,"Current",IF($M225<=30,"1-30",IF($M225<=60,"31-60",IF($M225<=90,"61-90","90+"))))) -> 1-30 | O225: =IF($H225="Outstanding",$G225,0) -> 29400 | P225: =$O225*IF($M225="",0,$M225) -> 411600
A226: INV-5225 | B226: Quarry & Co Wholesale | C226: ap@quarryco.com | D226: 46174 | E226: 30 | F226: 46204 | G226: 6450 | H226: Paid | I226: 46223 | J226: 6450 | K226: 49 | L226: 19 | M226: =IF($H226="Outstanding",MAX(0,Summary!$B$3-$F226),"") | N226: =IF($M226="","",IF($M226=0,"Current",IF($M226<=30,"1-30",IF($M226<=60,"31-60",IF($M226<=90,"61-90","90+"))))) | O226: =IF($H226="Outstanding",$G226,0) -> 0 | P226: =$O226*IF($M226="",0,$M226) -> 0
A227: INV-5226 | B227: Ridgeline Builders | C227: ap@ridgelinebuilders.com | D227: 46188 | E227: 30 | F227: 46218 | G227: 23900 | H227: Outstanding | J227: 0 | M227: =IF($H227="Outstanding",MAX(0,Summary!$B$3-$F227),"") -> 7 | N227: =IF($M227="","",IF($M227=0,"Current",IF($M227<=30,"1-30",IF($M227<=60,"31-60",IF($M227<=90,"61-90","90+"))))) -> 1-30 | O227: =IF($H227="Outstanding",$G227,0) -> 23900 | P227: =$O227*IF($M227="",0,$M227) -> 167300
A228: INV-5227 | B228: Northgate Property Mgmt | C228: vendors@northgatepm.com | D228: 46185 | E228: 30 | F228: 46215 | G228: 2600 | H228: Outstanding | J228: 0 | M228: =IF($H228="Outstanding",MAX(0,Summary!$B$3-$F228),"") -> 10 | N228: =IF($M228="","",IF($M228=0,"Current",IF($M228<=30,"1-30",IF($M228<=60,"31-60",IF($M228<=90,"61-90","90+"))))) -> 1-30 | O228: =IF($H228="Outstanding",$G228,0) -> 2600 | P228: =$O228*IF($M228="",0,$M228) -> 26000
A229: INV-5228 | B229: Pinewood Consulting | C229: amara@pinewoodconsulting.com | D229: 46196 | E229: 15 | F229: 46211 | G229: 4400 | H229: Paid | I229: 46212 | J229: 4400 | K229: 16 | L229: 1 | M229: =IF($H229="Outstanding",MAX(0,Summary!$B$3-$F229),"") | N229: =IF($M229="","",IF($M229=0,"Current",IF($M229<=30,"1-30",IF($M229<=60,"31-60",IF($M229<=90,"61-90","90+"))))) | O229: =IF($H229="Outstanding",$G229,0) -> 0 | P229: =$O229*IF($M229="",0,$M229) -> 0
A230: INV-5229 | B230: Lakeshore Events | C230: accounts@lakeshoreevents.com | D230: 46178 | E230: 30 | F230: 46208 | G230: 3800 | H230: Paid | I230: 46219 | J230: 3800 | K230: 41 | L230: 11 | M230: =IF($H230="Outstanding",MAX(0,Summary!$B$3-$F230),"") | N230: =IF($M230="","",IF($M230=0,"Current",IF($M230<=30,"1-30",IF($M230<=60,"31-60",IF($M230<=90,"61-90","90+"))))) | O230: =IF($H230="Outstanding",$G230,0) -> 0 | P230: =$O230*IF($M230="",0,$M230) -> 0
A231: INV-5230 | B231: Granite Civil Group | C231: ap@granitecivil.com | D231: 46196 | E231: 45 | F231: 46241 | G231: 31600 | H231: Outstanding | J231: 0 | M231: =IF($H231="Outstanding",MAX(0,Summary!$B$3-$F231),"") -> 0 | N231: =IF($M231="","",IF($M231=0,"Current",IF($M231<=30,"1-30",IF($M231<=60,"31-60",IF($M231<=90,"61-90","90+"))))) -> Current | O231: =IF($H231="Outstanding",$G231,0) -> 31600 | P231: =$O231*IF($M231="",0,$M231) -> 0
A232: INV-5231 | B232: Apex Mechanical | C232: accounts@apexmech.com | D232: 46198 | E232: 30 | F232: 46228 | G232: 6800 | H232: Outstanding | J232: 0 | M232: =IF($H232="Outstanding",MAX(0,Summary!$B$3-$F232),"") -> 0 | N232: =IF($M232="","",IF($M232=0,"Current",IF($M232<=30,"1-30",IF($M232<=60,"31-60",IF($M232<=90,"61-90","90+"))))) -> Current | O232: =IF($H232="Outstanding",$G232,0) -> 6800 | P232: =$O232*IF($M232="",0,$M232) -> 0
A233: INV-5232 | B233: Vantage Media Group | C233: ap@vantagemedia.group | D233: 46176 | E233: 30 | F233: 46206 | G233: 3250 | H233: Outstanding | J233: 0 | M233: =IF($H233="Outstanding",MAX(0,Summary!$B$3-$F233),"") -> 19 | N233: =IF($M233="","",IF($M233=0,"Current",IF($M233<=30,"1-30",IF($M233<=60,"31-60",IF($M233<=90,"61-90","90+"))))) -> 1-30 | O233: =IF($H233="Outstanding",$G233,0) -> 3250 | P233: =$O233*IF($M233="",0,$M233) -> 61750
A234: INV-5233 | B234: Cascade Logistics | C234: payables@cascadelogistics.com | D234: 46181 | E234: 30 | F234: 46211 | G234: 33050 | H234: Paid | I234: 46216 | J234: 33050 | K234: 35 | L234: 3 | M234: =IF($H234="Outstanding",MAX(0,Summary!$B$3-$F234),"") | N234: =IF($M234="","",IF($M234=0,"Current",IF($M234<=30,"1-30",IF($M234<=60,"31-60",IF($M234<=90,"61-90","90+"))))) | O234: =IF($H234="Outstanding",$G234,0) -> 0 | P234: =$O234*IF($M234="",0,$M234) -> 0
A235: INV-5234 | B235: Ridgeline Builders | C235: ap@ridgelinebuilders.com | D235: 46190 | E235: 30 | F235: 46220 | G235: 13600 | H235: Outstanding | J235: 0 | M235: =IF($H235="Outstanding",MAX(0,Summary!$B$3-$F235),"") -> 5 | N235: =IF($M235="","",IF($M235=0,"Current",IF($M235<=30,"1-30",IF($M235<=60,"31-60",IF($M235<=90,"61-90","90+"))))) -> 1-30 | O235: =IF($H235="Outstanding",$G235,0) -> 13600 | P235: =$O235*IF($M235="",0,$M235) -> 68000
A236: INV-5235 | B236: Bluefin Seafood Dist | C236: payables@bluefindist.com | D236: 46198 | E236: 30 | F236: 46228 | G236: 4000 | H236: Outstanding | J236: 0 | M236: =IF($H236="Outstanding",MAX(0,Summary!$B$3-$F236),"") -> 0 | N236: =IF($M236="","",IF($M236=0,"Current",IF($M236<=30,"1-30",IF($M236<=60,"31-60",IF($M236<=90,"61-90","90+"))))) -> Current | O236: =IF($H236="Outstanding",$G236,0) -> 4000 | P236: =$O236*IF($M236="",0,$M236) -> 0
A237: INV-5236 | B237: Meridian Health Partners | C237: billing@meridianhp.com | D237: 46188 | E237: 30 | F237: 46218 | G237: 10050 | H237: Outstanding | J237: 0 | M237: =IF($H237="Outstanding",MAX(0,Summary!$B$3-$F237),"") -> 7 | N237: =IF($M237="","",IF($M237=0,"Current",IF($M237<=30,"1-30",IF($M237<=60,"31-60",IF($M237<=90,"61-90","90+"))))) -> 1-30 | O237: =IF($H237="Outstanding",$G237,0) -> 10050 | P237: =$O237*IF($M237="",0,$M237) -> 70350
A238: INV-5237 | B238: Quarry & Co Wholesale | C238: ap@quarryco.com | D238: 46195 | E238: 30 | F238: 46225 | G238: 6850 | H238: Outstanding | J238: 0 | M238: =IF($H238="Outstanding",MAX(0,Summary!$B$3-$F238),"") -> 0 | N238: =IF($M238="","",IF($M238=0,"Current",IF($M238<=30,"1-30",IF($M238<=60,"31-60",IF($M238<=90,"61-90","90+"))))) -> Current | O238: =IF($H238="Outstanding",$G238,0) -> 6850 | P238: =$O238*IF($M238="",0,$M238) -> 0
A239: INV-5238 | B239: Harborline Interiors | C239: kim@harborlineinteriors.com | D239: 46223 | E239: 15 | F239: 46238 | G239: 2800 | H239: Outstanding | J239: 0 | M239: =IF($H239="Outstanding",MAX(0,Summary!$B$3-$F239),"") -> 0 | N239: =IF($M239="","",IF($M239=0,"Current",IF($M239<=30,"1-30",IF($M239<=60,"31-60",IF($M239<=90,"61-90","90+"))))) -> Current | O239: =IF($H239="Outstanding",$G239,0) -> 2800 | P239: =$O239*IF($M239="",0,$M239) -> 0
A240: INV-5239 | B240: Cascade Logistics | C240: payables@cascadelogistics.com | D240: 46224 | E240: 30 | F240: 46254 | G240: 23450 | H240: Outstanding | J240: 0 | M240: =IF($H240="Outstanding",MAX(0,Summary!$B$3-$F240),"") -> 0 | N240: =IF($M240="","",IF($M240=0,"Current",IF($M240<=30,"1-30",IF($M240<=60,"31-60",IF($M240<=90,"61-90","90+"))))) -> Current | O240: =IF($H240="Outstanding",$G240,0) -> 23450 | P240: =$O240*IF($M240="",0,$M240) -> 0
A241: INV-5240 | B241: Northgate Property Mgmt | C241: vendors@northgatepm.com | D241: 46217 | E241: 30 | F241: 46247 | G241: 1200 | H241: Outstanding | J241: 0 | M241: =IF($H241="Outstanding",MAX(0,Summary!$B$3-$F241),"") -> 0 | N241: =IF($M241="","",IF($M241=0,"Current",IF($M241<=30,"1-30",IF($M241<=60,"31-60",IF($M241<=90,"61-90","90+"))))) -> Current | O241: =IF($H241="Outstanding",$G241,0) -> 1200 | P241: =$O241*IF($M241="",0,$M241) -> 0
A242: INV-5241 | B242: Vantage Media Group | C242: ap@vantagemedia.group | D242: 46216 | E242: 30 | F242: 46246 | G242: 6150 | H242: Outstanding | J242: 0 | M242: =IF($H242="Outstanding",MAX(0,Summary!$B$3-$F242),"") -> 0 | N242: =IF($M242="","",IF($M242=0,"Current",IF($M242<=30,"1-30",IF($M242<=60,"31-60",IF($M242<=90,"61-90","90+"))))) -> Current | O242: =IF($H242="Outstanding",$G242,0) -> 6150 | P242: =$O242*IF($M242="",0,$M242) -> 0
A243: INV-5242 | B243: Quarry & Co Wholesale | C243: ap@quarryco.com | D243: 46206 | E243: 30 | F243: 46236 | G243: 7450 | H243: Outstanding | J243: 0 | M243: =IF($H243="Outstanding",MAX(0,Summary!$B$3-$F243),"") -> 0 | N243: =IF($M243="","",IF($M243=0,"Current",IF($M243<=30,"1-30",IF($M243<=60,"31-60",IF($M243<=90,"61-90","90+"))))) -> Current | O243: =IF($H243="Outstanding",$G243,0) -> 7450 | P243: =$O243*IF($M243="",0,$M243) -> 0
A244: INV-5243 | B244: Lakeshore Events | C244: accounts@lakeshoreevents.com | D244: 46216 | E244: 30 | F244: 46246 | G244: 2900 | H244: Outstanding | J244: 0 | M244: =IF($H244="Outstanding",MAX(0,Summary!$B$3-$F244),"") -> 0 | N244: =IF($M244="","",IF($M244=0,"Current",IF($M244<=30,"1-30",IF($M244<=60,"31-60",IF($M244<=90,"61-90","90+"))))) -> Current | O244: =IF($H244="Outstanding",$G244,0) -> 2900 | P244: =$O244*IF($M244="",0,$M244) -> 0
A245: INV-5244 | B245: Stellar Staffing Co | C245: finance@stellarstaffing.co | D245: 46220 | E245: 15 | F245: 46235 | G245: 14400 | H245: Outstanding | J245: 0 | M245: =IF($H245="Outstanding",MAX(0,Summary!$B$3-$F245),"") -> 0 | N245: =IF($M245="","",IF($M245=0,"Current",IF($M245<=30,"1-30",IF($M245<=60,"31-60",IF($M245<=90,"61-90","90+"))))) -> Current | O245: =IF($H245="Outstanding",$G245,0) -> 14400 | P245: =$O245*IF($M245="",0,$M245) -> 0
A246: INV-5245 | B246: Northgate Property Mgmt | C246: vendors@northgatepm.com | D246: 46216 | E246: 30 | F246: 46246 | G246: 6700 | H246: Outstanding | J246: 0 | M246: =IF($H246="Outstanding",MAX(0,Summary!$B$3-$F246),"") -> 0 | N246: =IF($M246="","",IF($M246=0,"Current",IF($M246<=30,"1-30",IF($M246<=60,"31-60",IF($M246<=90,"61-90","90+"))))) -> Current | O246: =IF($H246="Outstanding",$G246,0) -> 6700 | P246: =$O246*IF($M246="",0,$M246) -> 0
A247: INV-5246 | B247: BlueRidge Hotels | C247: karen.wu@blueridgehotels.com | D247: 46216 | E247: 30 | F247: 46246 | G247: 9050 | H247: Outstanding | J247: 0 | M247: =IF($H247="Outstanding",MAX(0,Summary!$B$3-$F247),"") -> 0 | N247: =IF($M247="","",IF($M247=0,"Current",IF($M247<=30,"1-30",IF($M247<=60,"31-60",IF($M247<=90,"61-90","90+"))))) -> Current | O247: =IF($H247="Outstanding",$G247,0) -> 9050 | P247: =$O247*IF($M247="",0,$M247) -> 0
A248: INV-5247 | B248: Pinewood Consulting | C248: amara@pinewoodconsulting.com | D248: 46204 | E248: 15 | F248: 46219 | G248: 3100 | H248: Paid | I248: 46223 | J248: 3100 | K248: 19 | L248: 2 | M248: =IF($H248="Outstanding",MAX(0,Summary!$B$3-$F248),"") | N248: =IF($M248="","",IF($M248=0,"Current",IF($M248<=30,"1-30",IF($M248<=60,"31-60",IF($M248<=90,"61-90","90+"))))) | O248: =IF($H248="Outstanding",$G248,0) -> 0 | P248: =$O248*IF($M248="",0,$M248) -> 0
A249: INV-5248 | B249: Foundry Dev Collective | C249: ops@foundrydev.co | D249: 46225 | E249: 30 | F249: 46255 | G249: 24700 | H249: Outstanding | J249: 0 | M249: =IF($H249="Outstanding",MAX(0,Summary!$B$3-$F249),"") -> 0 | N249: =IF($M249="","",IF($M249=0,"Current",IF($M249<=30,"1-30",IF($M249<=60,"31-60",IF($M249<=90,"61-90","90+"))))) -> Current | O249: =IF($H249="Outstanding",$G249,0) -> 24700 | P249: =$O249*IF($M249="",0,$M249) -> 0
A250: INV-5249 | B250: Vantage Media Group | C250: ap@vantagemedia.group | D250: 46227 | E250: 30 | F250: 46257 | G250: 12850 | H250: Outstanding | J250: 0 | M250: =IF($H250="Outstanding",MAX(0,Summary!$B$3-$F250),"") -> 0 | N250: =IF($M250="","",IF($M250=0,"Current",IF($M250<=30,"1-30",IF($M250<=60,"31-60",IF($M250<=90,"61-90","90+"))))) -> Current | O250: =IF($H250="Outstanding",$G250,0) -> 12850 | P250: =$O250*IF($M250="",0,$M250) -> 0
A251: INV-5250 | B251: Meridian Health Partners | C251: billing@meridianhp.com | D251: 46216 | E251: 30 | F251: 46246 | G251: 11950 | H251: Outstanding | J251: 0 | M251: =IF($H251="Outstanding",MAX(0,Summary!$B$3-$F251),"") -> 0 | N251: =IF($M251="","",IF($M251=0,"Current",IF($M251<=30,"1-30",IF($M251<=60,"31-60",IF($M251<=90,"61-90","90+"))))) -> Current | O251: =IF($H251="Outstanding",$G251,0) -> 11950 | P251: =$O251*IF($M251="",0,$M251) -> 0

Sheet Summary
A1: AR Aging & Payment Behavior Analysis
A2: Demo dataset: 250 historical invoices, Jan 2025 - Jul 2026. All names and figures are fictional.
A3: Analysis date: | B3: 46225 | C3: (blue on yellow = editable input; everything else is formula-driven)
A5: Headline numbers
A6: Invoices in dump | B6: =COUNTA(Data!$A$2:$A$251) -> 250
A7: Invoices paid | B7: =SUMPRODUCT(--(LEFT(Data!$H$2:$H$251,4)="Paid")) -> 219
A8: Invoices outstanding | B8: =COUNTIF(Data!$H$2:$H$251,"Outstanding") -> 31
A9: Total billed (18 months) | B9: =SUM(Data!$G$2:$G$251) -> 2575650
A10: Average monthly billing | B10: =B9/19 -> 135560.53
A11: Open AR today | B11: =SUM(Data!$O$2:$O$251) -> 407550
A12: Value-weighted avg days to pay (paid invoices) | B12: =SUMPRODUCT((LEFT(Data!$H$2:$H$251,4)="Paid")*Data!$K$2:$K$251*Data!$G$2:$G$251)/SUMPRODUCT((LEFT(Data!$H$2:$H$251,4)="Paid")*Data!$G$2:$G$251) -> 49.609428
A13: Value-weighted avg credit terms | B13: =SUMPRODUCT(Data!$E$2:$E$251*Data!$G$2:$G$251)/SUM(Data!$G$2:$G$251) -> 30.374469
A14: Extra credit days granted beyond terms | B14: =B12-B13 -> 19.234959
A15: Cash locked by slow collection (approx.) | B15: =B10*(B14/30) -> 86916.706
A16: The sentence that matters (auto-built):
A17: ="You collect at "&TEXT(B12,"0.0")&" days against "&TEXT(B13,"0")&"-day terms. That gap parks roughly "&TEXT(B15,"$#,##0")&" of your cash with customers, permanently." -> You collect at 49.6 days against 30-day terms. That gap parks roughly $86,917 of your cash with customers, permanently.
A19: Aging of open AR
A20: Current | B20: =SUMIF(Data!$N$2:$N$251,"Current",Data!$O$2:$O$251) -> 172850 | C20: =IFERROR(B20/$B$11,0) -> 0.42411974
A21: 1-30 | B21: =SUMIF(Data!$N$2:$N$251,"1-30",Data!$O$2:$O$251) -> 109050 | C21: =IFERROR(B21/$B$11,0) -> 0.26757453
A22: 31-60 | B22: =SUMIF(Data!$N$2:$N$251,"31-60",Data!$O$2:$O$251) -> 37500 | C22: =IFERROR(B22/$B$11,0) -> 0.09201325
A23: 61-90 | B23: =SUMIF(Data!$N$2:$N$251,"61-90",Data!$O$2:$O$251) -> 22050 | C23: =IFERROR(B23/$B$11,0) -> 0.054103791
A24: 90+ | B24: =SUMIF(Data!$N$2:$N$251,"90+",Data!$O$2:$O$251) -> 66100 | C24: =IFERROR(B24/$B$11,0) -> 0.16218869

Sheet AgingByCustomer
A1: Customer | B1: Open # | C1: Current | D1: 1-30 | E1: 31-60 | F1: 61-90 | G1: 90+ | H1: Total open | I1: Value-weighted age (days)
A2: Ridgeline Builders | B2: =COUNTIFS(Data!$B$2:$B$251,$A2,Data!$H$2:$H$251,"Outstanding") -> 6 | C2: =SUMIFS(Data!$O$2:$O$251,Data!$B$2:$B$251,$A2,Data!$N$2:$N$251,"Current") -> 0 | D2: =SUMIFS(Data!$O$2:$O$251,Data!$B$2:$B$251,$A2,Data!$N$2:$N$251,"1-30") -> 37500 | E2: =SUMIFS(Data!$O$2:$O$251,Data!$B$2:$B$251,$A2,Data!$N$2:$N$251,"31-60") -> 18950 | F2: =SUMIFS(Data!$O$2:$O$251,Data!$B$2:$B$251,$A2,Data!$N$2:$N$251,"61-90") -> 0 | G2: =SUMIFS(Data!$O$2:$O$251,Data!$B$2:$B$251,$A2,Data!$N$2:$N$251,"90+") -> 58750 | H2: =SUMIFS(Data!$O$2:$O$251,Data!$B$2:$B$251,$A2) -> 115200 | I2: =IFERROR(SUMIFS(Data!$P$2:$P$251,Data!$B$2:$B$251,$A2)/H2,0) -> 61.877604
A3: Granite Civil Group | B3: =COUNTIFS(Data!$B$2:$B$251,$A3,Data!$H$2:$H$251,"Outstanding") -> 3 | C3: =SUMIFS(Data!$O$2:$O$251,Data!$B$2:$B$251,$A3,Data!$N$2:$N$251,"Current") -> 31600 | D3: =SUMIFS(Data!$O$2:$O$251,Data!$B$2:$B$251,$A3,Data!$N$2:$N$251,"1-30") -> 26250 | E3: =SUMIFS(Data!$O$2:$O$251,Data!$B$2:$B$251,$A3,Data!$N$2:$N$251,"31-60") -> 0 | F3: =SUMIFS(Data!$O$2:$O$251,Data!$B$2:$B$251,$A3,Data!$N$2:$N$251,"61-90") -> 22050 | G3: =SUMIFS(Data!$O$2:$O$251,Data!$B$2:$B$251,$A3,Data!$N$2:$N$251,"90+") -> 0 | H3: =SUMIFS(Data!$O$2:$O$251,Data!$B$2:$B$251,$A3) -> 79900 | I3: =IFERROR(SUMIFS(Data!$P$2:$P$251,Data!$B$2:$B$251,$A3)/H3,0) -> 28.00438
A4: Foundry Dev Collective | B4: =COUNTIFS(Data!$B$2:$B$251,$A4,Data!$H$2:$H$251,"Outstanding") -> 2 | C4: =SUMIFS(Data!$O$2:$O$251,Data!$B$2:$B$251,$A4,Data!$N$2:$N$251,"Current") -> 24700 | D4: =SUMIFS(Data!$O$2:$O$251,Data!$B$2:$B$251,$A4,Data!$N$2:$N$251,"1-30") -> 29400 | E4: =SUMIFS(Data!$O$2:$O$251,Data!$B$2:$B$251,$A4,Data!$N$2:$N$251,"31-60") -> 0 | F4: =SUMIFS(Data!$O$2:$O$251,Data!$B$2:$B$251,$A4,Data!$N$2:$N$251,"61-90") -> 0 | G4: =SUMIFS(Data!$O$2:$O$251,Data!$B$2:$B$251,$A4,Data!$N$2:$N$251,"90+") -> 0 | H4: =SUMIFS(Data!$O$2:$O$251,Data!$B$2:$B$251,$A4) -> 54100 | I4: =IFERROR(SUMIFS(Data!$P$2:$P$251,Data!$B$2:$B$251,$A4)/H4,0) -> 7.6081331
A5: Vantage Media Group | B5: =COUNTIFS(Data!$B$2:$B$251,$A5,Data!$H$2:$H$251,"Outstanding") -> 4 | C5: =SUMIFS(Data!$O$2:$O$251,Data!$B$2:$B$251,$A5,Data!$N$2:$N$251,"Current") -> 19000 | D5: =SUMIFS(Data!$O$2:$O$251,Data!$B$2:$B$251,$A5,Data!$N$2:$N$251,"1-30") -> 3250 | E5: =SUMIFS(Data!$O$2:$O$251,Data!$B$2:$B$251,$A5,Data!$N$2:$N$251,"31-60") -> 0 | F5: =SUMIFS(Data!$O$2:$O$251,Data!$B$2:$B$251,$A5,Data!$N$2:$N$251,"61-90") -> 0 | G5: =SUMIFS(Data!$O$2:$O$251,Data!$B$2:$B$251,$A5,Data!$N$2:$N$251,"90+") -> 5050 | H5: =SUMIFS(Data!$O$2:$O$251,Data!$B$2:$B$251,$A5) -> 27300 | I5: =IFERROR(SUMIFS(Data!$P$2:$P$251,Data!$B$2:$B$251,$A5)/H5,0) -> 19.650183
A6: Cascade Logistics | B6: =COUNTIFS(Data!$B$2:$B$251,$A6,Data!$H$2:$H$251,"Outstanding") -> 1 | C6: =SUMIFS(Data!$O$2:$O$251,Data!$B$2:$B$251,$A6,Data!$N$2:$N$251,"Current") -> 23450 | D6: =SUMIFS(Data!$O$2:$O$251,Data!$B$2:$B$251,$A6,Data!$N$2:$N$251,"1-30") -> 0 | E6: =SUMIFS(Data!$O$2:$O$251,Data!$B$2:$B$251,$A6,Data!$N$2:$N$251,"31-60") -> 0 | F6: =SUMIFS(Data!$O$2:$O$251,Data!$B$2:$B$251,$A6,Data!$N$2:$N$251,"61-90") -> 0 | G6: =SUMIFS(Data!$O$2:$O$251,Data!$B$2:$B$251,$A6,Data!$N$2:$N$251,"90+") -> 0 | H6: =SUMIFS(Data!$O$2:$O$251,Data!$B$2:$B$251,$A6) -> 23450 | I6: =IFERROR(SUMIFS(Data!$P$2:$P$251,Data!$B$2:$B$251,$A6)/H6,0) -> 0
A7: Meridian Health Partners | B7: =COUNTIFS(Data!$B$2:$B$251,$A7,Data!$H$2:$H$251,"Outstanding") -> 2 | C7: =SUMIFS(Data!$O$2:$O$251,Data!$B$2:$B$251,$A7,Data!$N$2:$N$251,"Current") -> 11950 | D7: =SUMIFS(Data!$O$2:$O$251,Data!$B$2:$B$251,$A7,Data!$N$2:$N$251,"1-30") -> 10050 | E7: =SUMIFS(Data!$O$2:$O$251,Data!$B$2:$B$251,$A7,Data!$N$2:$N$251,"31-60") -> 0 | F7: =SUMIFS(Data!$O$2:$O$251,Data!$B$2:$B$251,$A7,Data!$N$2:$N$251,"61-90") -> 0 | G7: =SUMIFS(Data!$O$2:$O$251,Data!$B$2:$B$251,$A7,Data!$N$2:$N$251,"90+") -> 0 | H7: =SUMIFS(Data!$O$2:$O$251,Data!$B$2:$B$251,$A7) -> 22000 | I7: =IFERROR(SUMIFS(Data!$P$2:$P$251,Data!$B$2:$B$251,$A7)/H7,0) -> 3.1977273
A8: Seoul Pharma Trading | B8: =COUNTIFS(Data!$B$2:$B$251,$A8,Data!$H$2:$H$251,"Outstanding") -> 1 | C8: =SUMIFS(Data!$O$2:$O$251,Data!$B$2:$B$251,$A8,Data!$N$2:$N$251,"Current") -> 0 | D8: =SUMIFS(Data!$O$2:$O$251,Data!$B$2:$B$251,$A8,Data!$N$2:$N$251,"1-30") -> 0 | E8: =SUMIFS(Data!$O$2:$O$251,Data!$B$2:$B$251,$A8,Data!$N$2:$N$251,"31-60") -> 18550 | F8: =SUMIFS(Data!$O$2:$O$251,Data!$B$2:$B$251,$A8,Data!$N$2:$N$251,"61-90") -> 0 | G8: =SUMIFS(Data!$O$2:$O$251,Data!$B$2:$B$251,$A8,Data!$N$2:$N$251,"90+") -> 0 | H8: =SUMIFS(Data!$O$2:$O$251,Data!$B$2:$B$251,$A8) -> 18550 | I8: =IFERROR(SUMIFS(Data!$P$2:$P$251,Data!$B$2:$B$251,$A8)/H8,0) -> 35
A9: Stellar Staffing Co | B9: =COUNTIFS(Data!$B$2:$B$251,$A9,Data!$H$2:$H$251,"Outstanding") -> 1 | C9: =SUMIFS(Data!$O$2:$O$251,Data!$B$2:$B$251,$A9,Data!$N$2:$N$251,"Current") -> 14400 | D9: =SUMIFS(Data!$O$2:$O$251,Data!$B$2:$B$251,$A9,Data!$N$2:$N$251,"1-30") -> 0 | E9: =SUMIFS(Data!$O$2:$O$251,Data!$B$2:$B$251,$A9,Data!$N$2:$N$251,"31-60") -> 0 | F9: =SUMIFS(Data!$O$2:$O$251,Data!$B$2:$B$251,$A9,Data!$N$2:$N$251,"61-90") -> 0 | G9: =SUMIFS(Data!$O$2:$O$251,Data!$B$2:$B$251,$A9,Data!$N$2:$N$251,"90+") -> 0 | H9: =SUMIFS(Data!$O$2:$O$251,Data!$B$2:$B$251,$A9) -> 14400 | I9: =IFERROR(SUMIFS(Data!$P$2:$P$251,Data!$B$2:$B$251,$A9)/H9,0) -> 0
A10: Quarry & Co Wholesale | B10: =COUNTIFS(Data!$B$2:$B$251,$A10,Data!$H$2:$H$251,"Outstanding") -> 2 | C10: =SUMIFS(Data!$O$2:$O$251,Data!$B$2:$B$251,$A10,Data!$N$2:$N$251,"Current") -> 14300 | D10: =SUMIFS(Data!$O$2:$O$251,Data!$B$2:$B$251,$A10,Data!$N$2:$N$251,"1-30") -> 0 | E10: =SUMIFS(Data!$O$2:$O$251,Data!$B$2:$B$251,$A10,Data!$N$2:$N$251,"31-60") -> 0 | F10: =SUMIFS(Data!$O$2:$O$251,Data!$B$2:$B$251,$A10,Data!$N$2:$N$251,"61-90") -> 0 | G10: =SUMIFS(Data!$O$2:$O$251,Data!$B$2:$B$251,$A10,Data!$N$2:$N$251,"90+") -> 0 | H10: =SUMIFS(Data!$O$2:$O$251,Data!$B$2:$B$251,$A10) -> 14300 | I10: =IFERROR(SUMIFS(Data!$P$2:$P$251,Data!$B$2:$B$251,$A10)/H10,0) -> 0
A11: Northgate Property Mgmt | B11: =COUNTIFS(Data!$B$2:$B$251,$A11,Data!$H$2:$H$251,"Outstanding") -> 4 | C11: =SUMIFS(Data!$O$2:$O$251,Data!$B$2:$B$251,$A11,Data!$N$2:$N$251,"Current") -> 7900 | D11: =SUMIFS(Data!$O$2:$O$251,Data!$B$2:$B$251,$A11,Data!$N$2:$N$251,"1-30") -> 2600 | E11: =SUMIFS(Data!$O$2:$O$251,Data!$B$2:$B$251,$A11,Data!$N$2:$N$251,"31-60") -> 0 | F11: =SUMIFS(Data!$O$2:$O$251,Data!$B$2:$B$251,$A11,Data!$N$2:$N$251,"61-90") -> 0 | G11: =SUMIFS(Data!$O$2:$O$251,Data!$B$2:$B$251,$A11,Data!$N$2:$N$251,"90+") -> 2300 | H11: =SUMIFS(Data!$O$2:$O$251,Data!$B$2:$B$251,$A11) -> 12800 | I11: =IFERROR(SUMIFS(Data!$P$2:$P$251,Data!$B$2:$B$251,$A11)/H11,0) -> 25.929688
A12: BlueRidge Hotels | B12: =COUNTIFS(Data!$B$2:$B$251,$A12,Data!$H$2:$H$251,"Outstanding") -> 1 | C12: =SUMIFS(Data!$O$2:$O$251,Data!$B$2:$B$251,$A12,Data!$N$2:$N$251,"Current") -> 9050 | D12: =SUMIFS(Data!$O$2:$O$251,Data!$B$2:$B$251,$A12,Data!$N$2:$N$251,"1-30") -> 0 | E12: =SUMIFS(Data!$O$2:$O$251,Data!$B$2:$B$251,$A12,Data!$N$2:$N$251,"31-60") -> 0 | F12: =SUMIFS(Data!$O$2:$O$251,Data!$B$2:$B$251,$A12,Data!$N$2:$N$251,"61-90") -> 0 | G12: =SUMIFS(Data!$O$2:$O$251,Data!$B$2:$B$251,$A12,Data!$N$2:$N$251,"90+") -> 0 | H12: =SUMIFS(Data!$O$2:$O$251,Data!$B$2:$B$251,$A12) -> 9050 | I12: =IFERROR(SUMIFS(Data!$P$2:$P$251,Data!$B$2:$B$251,$A12)/H12,0) -> 0
A13: Apex Mechanical | B13: =COUNTIFS(Data!$B$2:$B$251,$A13,Data!$H$2:$H$251,"Outstanding") -> 1 | C13: =SUMIFS(Data!$O$2:$O$251,Data!$B$2:$B$251,$A13,Data!$N$2:$N$251,"Current") -> 6800 | D13: =SUMIFS(Data!$O$2:$O$251,Data!$B$2:$B$251,$A13,Data!$N$2:$N$251,"1-30") -> 0 | E13: =SUMIFS(Data!$O$2:$O$251,Data!$B$2:$B$251,$A13,Data!$N$2:$N$251,"31-60") -> 0 | F13: =SUMIFS(Data!$O$2:$O$251,Data!$B$2:$B$251,$A13,Data!$N$2:$N$251,"61-90") -> 0 | G13: =SUMIFS(Data!$O$2:$O$251,Data!$B$2:$B$251,$A13,Data!$N$2:$N$251,"90+") -> 0 | H13: =SUMIFS(Data!$O$2:$O$251,Data!$B$2:$B$251,$A13) -> 6800 | I13: =IFERROR(SUMIFS(Data!$P$2:$P$251,Data!$B$2:$B$251,$A13)/H13,0) -> 0
... A19: Orchid Labs | B19: =COUNTIFS(Data!$B$2:$B$251,$A19,Data!$H$2:$H$251,"Outstanding") -> 0 | C19: =SUMIFS(Data!$O$2:$O$251,Data!$B$2:$B$251,$A19,Data!$N$2:$N$251,"Current") -> 0 | D19: =SUMIFS(Data!$O$2:$O$251,Data!$B$2:$B$251,$A19,Data!$N$2:$N$251,"1-30") -> 0 | E19: =SUMIFS(Data!$O$2:$O$251,Data!$B$2:$B$251,$A19,Data!$N$2:$N$251,"31-60") -> 0 | F19: =SUMIFS(Data!$O$2:$O$251,Data!$B$2:$B$251,$A19,Data!$N$2:$N$251,"61-90") -> 0 | G19: =SUMIFS(Data!$O$2:$O$251,Data!$B$2:$B$251,$A19,Data!$N$2:$N$251,"90+") -> 0 | H19: =SUMIFS(Data!$O$2:$O$251,Data!$B$2:$B$251,$A19) -> 0 | I19: =IFERROR(SUMIFS(Data!$P$2:$P$251,Data!$B$2:$B$251,$A19)/H19,0) -> 0
A20: TOTAL | B20: =SUM(B2:B19) -> 31 | C20: =SUM(C2:C19) -> 172850 | D20: =SUM(D2:D19) -> 109050 | E20: =SUM(E2:E19) -> 37500 | F20: =SUM(F2:F19) -> 22050 | G20: =SUM(G2:G19) -> 66100 | H20: =SUM(H2:H19) -> 407550

Sheet CustomerBehavior
A1: Customer | B1: Invoices (18 mo) | C1: Lifetime billed | D1: Avg days to pay | E1: Terms (days) | F1: Avg days late | G1: Late trend (2nd half vs 1st, days) | H1: Behavior read
A2: Ridgeline Builders | B2: =COUNTIF(Data!$B$2:$B$251,$A2) -> 15 | C2: =SUMIF(Data!$B$2:$B$251,$A2,Data!$G$2:$G$251) -> 225200 | D2: =IFERROR(AVERAGEIFS(Data!$K$2:$K$251,Data!$B$2:$B$251,$A2,Data!$H$2:$H$251,"Paid*"),"n/a") -> 69.222222 | E2: 30 | F2: =IFERROR(AVERAGEIFS(Data!$L$2:$L$251,Data!$B$2:$B$251,$A2,Data!$H$2:$H$251,"Paid*"),"n/a") -> 38.555556 | G2: 4.1 | H2: Problem payer, account-level intervention required
A3: Granite Civil Group | B3: =COUNTIF(Data!$B$2:$B$251,$A3) -> 12 | C3: =SUMIF(Data!$B$2:$B$251,$A3,Data!$G$2:$G$251) -> 299500 | D3: =IFERROR(AVERAGEIFS(Data!$K$2:$K$251,Data!$B$2:$B$251,$A3,Data!$H$2:$H$251,"Paid*"),"n/a") -> 70.444444 | E3: 45 | F3: =IFERROR(AVERAGEIFS(Data!$L$2:$L$251,Data!$B$2:$B$251,$A3,Data!$H$2:$H$251,"Paid*"),"n/a") -> 25.444444 | G3: -1.9 | H3: Chronically slow, needs firm consistent follow-up
A4: Foundry Dev Collective | B4: =COUNTIF(Data!$B$2:$B$251,$A4) -> 13 | C4: =SUMIF(Data!$B$2:$B$251,$A4,Data!$G$2:$G$251) -> 291900 | D4: =IFERROR(AVERAGEIFS(Data!$K$2:$K$251,Data!$B$2:$B$251,$A4,Data!$H$2:$H$251,"Paid*"),"n/a") -> 40.636364 | E4: 30 | F4: =IFERROR(AVERAGEIFS(Data!$L$2:$L$251,Data!$B$2:$B$251,$A4,Data!$H$2:$H$251,"Paid*"),"n/a") -> 9.7272727 | G4: 4.3 | H4: Mildly slow, standard cadence works
A5: Vantage Media Group | B5: =COUNTIF(Data!$B$2:$B$251,$A5) -> 14 | C5: =SUMIF(Data!$B$2:$B$251,$A5,Data!$G$2:$G$251) -> 108600 | D5: =IFERROR(AVERAGEIFS(Data!$K$2:$K$251,Data!$B$2:$B$251,$A5,Data!$H$2:$H$251,"Paid*"),"n/a") -> 89.7 | E5: 30 | F5: =IFERROR(AVERAGEIFS(Data!$L$2:$L$251,Data!$B$2:$B$251,$A5,Data!$H$2:$H$251,"Paid*"),"n/a") -> 58.9 | G5: 4.6 | H5: Problem payer, account-level intervention required
A6: Cascade Logistics | B6: =COUNTIF(Data!$B$2:$B$251,$A6) -> 13 | C6: =SUMIF(Data!$B$2:$B$251,$A6,Data!$G$2:$G$251) -> 308850 | D6: =IFERROR(AVERAGEIFS(Data!$K$2:$K$251,Data!$B$2:$B$251,$A6,Data!$H$2:$H$251,"Paid*"),"n/a") -> 40 | E6: 30 | F6: =IFERROR(AVERAGEIFS(Data!$L$2:$L$251,Data!$B$2:$B$251,$A6,Data!$H$2:$H$251,"Paid*"),"n/a") -> 9.4166667 | G6: -3.8 | H6: Mildly slow, standard cadence works
A7: Meridian Health Partners | B7: =COUNTIF(Data!$B$2:$B$251,$A7) -> 16 | C7: =SUMIF(Data!$B$2:$B$251,$A7,Data!$G$2:$G$251) -> 147100 | D7: =IFERROR(AVERAGEIFS(Data!$K$2:$K$251,Data!$B$2:$B$251,$A7,Data!$H$2:$H$251,"Paid*"),"n/a") -> 44.928571 | E7: 30 | F7: =IFERROR(AVERAGEIFS(Data!$L$2:$L$251,Data!$B$2:$B$251,$A7,Data!$H$2:$H$251,"Paid*"),"n/a") -> 14.714286 | G7: 11.1 | H7: Mildly slow, standard cadence works | DETERIORATING, investigate now
A8: Seoul Pharma Trading | B8: =COUNTIF(Data!$B$2:$B$251,$A8) -> 17 | C8: =SUMIF(Data!$B$2:$B$251,$A8,Data!$G$2:$G$251) -> 201900 | D8: =IFERROR(AVERAGEIFS(Data!$K$2:$K$251,Data!$B$2:$B$251,$A8,Data!$H$2:$H$251,"Paid*"),"n/a") -> 65.6875 | E8: 30 | F8: =IFERROR(AVERAGEIFS(Data!$L$2:$L$251,Data!$B$2:$B$251,$A8,Data!$H$2:$H$251,"Paid*"),"n/a") -> 35.4375 | G8: 8.1 | H8: Problem payer, account-level intervention required | DETERIORATING, investigate now
A9: Stellar Staffing Co | B9: =COUNTIF(Data!$B$2:$B$251,$A9) -> 8 | C9: =SUMIF(Data!$B$2:$B$251,$A9,Data!$G$2:$G$251) -> 104300 | D9: =IFERROR(AVERAGEIFS(Data!$K$2:$K$251,Data!$B$2:$B$251,$A9,Data!$H$2:$H$251,"Paid*"),"n/a") -> 18.714286 | E9: 15 | F9: =IFERROR(AVERAGEIFS(Data!$L$2:$L$251,Data!$B$2:$B$251,$A9,Data!$H$2:$H$251,"Paid*"),"n/a") -> 3.2857143 | G9: 0.5 | H9: Reliable payer, protect the relationship
A10: Quarry & Co Wholesale | B10: =COUNTIF(Data!$B$2:$B$251,$A10) -> 20 | C10: =SUMIF(Data!$B$2:$B$251,$A10,Data!$G$2:$G$251) -> 138950 | D10: =IFERROR(AVERAGEIFS(Data!$K$2:$K$251,Data!$B$2:$B$251,$A10,Data!$H$2:$H$251,"Paid*"),"n/a") -> 55.777778 | E10: 30 | F10: =IFERROR(AVERAGEIFS(Data!$L$2:$L$251,Data!$B$2:$B$251,$A10,Data!$H$2:$H$251,"Paid*"),"n/a") -> 25.277778 | G10: -6.8 | H10: Chronically slow, needs firm consistent follow-up
A11: Northgate Property Mgmt | B11: =COUNTIF(Data!$B$2:$B$251,$A11) -> 20 | C11: =SUMIF(Data!$B$2:$B$251,$A11,Data!$G$2:$G$251) -> 82650 | D11: =IFERROR(AVERAGEIFS(Data!$K$2:$K$251,Data!$B$2:$B$251,$A11,Data!$H$2:$H$251,"Paid*"),"n/a") -> 74 | E11: 30 | F11: =IFERROR(AVERAGEIFS(Data!$L$2:$L$251,Data!$B$2:$B$251,$A11,Data!$H$2:$H$251,"Paid*"),"n/a") -> 43.625 | G11: -6.2 | H11: Problem payer, account-level intervention required
A12: BlueRidge Hotels | B12: =COUNTIF(Data!$B$2:$B$251,$A12) -> 20 | C12: =SUMIF(Data!$B$2:$B$251,$A12,Data!$G$2:$G$251) -> 240850 | D12: =IFERROR(AVERAGEIFS(Data!$K$2:$K$251,Data!$B$2:$B$251,$A12,Data!$H$2:$H$251,"Paid*"),"n/a") -> 45.315789 | E12: 30 | F12: =IFERROR(AVERAGEIFS(Data!$L$2:$L$251,Data!$B$2:$B$251,$A12,Data!$H$2:$H$251,"Paid*"),"n/a") -> 14.684211 | G12: 3 | H12: Mildly slow, standard cadence works
A13: Apex Mechanical | B13: =COUNTIF(Data!$B$2:$B$251,$A13) -> 17 | C13: =SUMIF(Data!$B$2:$B$251,$A13,Data!$G$2:$G$251) -> 85300 | D13: =IFERROR(AVERAGEIFS(Data!$K$2:$K$251,Data!$B$2:$B$251,$A13,Data!$H$2:$H$251,"Paid*"),"n/a") -> 35 | E13: 30 | F13: =IFERROR(AVERAGEIFS(Data!$L$2:$L$251,Data!$B$2:$B$251,$A13,Data!$H$2:$H$251,"Paid*"),"n/a") -> 4.5625 | G13: -2.9 | H13: Reliable payer, protect the relationship
... A19: Orchid Labs | B19: =COUNTIF(Data!$B$2:$B$251,$A19) -> 7 | C19: =SUMIF(Data!$B$2:$B$251,$A19,Data!$G$2:$G$251) -> 50550 | D19: =IFERROR(AVERAGEIFS(Data!$K$2:$K$251,Data!$B$2:$B$251,$A19,Data!$H$2:$H$251,"Paid*"),"n/a") -> 40.857143 | E19: 30 | F19: =IFERROR(AVERAGEIFS(Data!$L$2:$L$251,Data!$B$2:$B$251,$A19,Data!$H$2:$H$251,"Paid*"),"n/a") -> 10.285714 | G19: -0.7 | H19: Mildly slow, standard cadence works
A21: Note: 'Late trend' is computed in the source dump (average lateness of the customer's second half of paid invoices minus the first half). Positive = getting slower. Hardcoded blue by design; recompute from Data when refreshed.

Sheet PriorityTop10
A1: Where the energy goes: top 10 by cash impact, not by metric
A2: Impact = open value x value-weighted age. A $100 invoice 100 days old never outranks a $30K invoice 45 days old.
A4: Rank | B4: Customer | C4: Open value | D4: Value-weighted age | E4: Impact score | F4: Avg late (hist.) | G4: Recommended first move
A5: 1 | B5: Ridgeline Builders | C5: =AgingByCustomer!H2 -> 115200 | D5: =AgingByCustomer!I2 -> 61.877604 | E5: =C5*MAX(1,D5) -> 7128300 | F5: =IFERROR(AVERAGEIFS(Data!$L$2:$L$251,Data!$B$2:$B$251,$B5,Data!$H$2:$H$251,"Paid*"),"n/a") -> 38.555556 | G5: Account-level call today; consolidate all open invoices into one written plan (history: honors plans).
A6: 2 | B6: Granite Civil Group | C6: =AgingByCustomer!H3 -> 79900 | D6: =AgingByCustomer!I3 -> 28.00438 | E6: =C6*MAX(1,D6) -> 2237550 | F6: =IFERROR(AVERAGEIFS(Data!$L$2:$L$251,Data!$B$2:$B$251,$B6,Data!$H$2:$H$251,"Paid*"),"n/a") -> 25.444444 | G6: Confirm retainage/release milestones in writing; escalate the 90+ item with a dated final notice.
A7: 3 | B7: Seoul Pharma Trading | C7: =AgingByCustomer!H8 -> 18550 | D7: =AgingByCustomer!I8 -> 35 | E7: =C7*MAX(1,D7) -> 649250 | F7: =IFERROR(AVERAGEIFS(Data!$L$2:$L$251,Data!$B$2:$B$251,$B7,Data!$H$2:$H$251,"Paid*"),"n/a") -> 35.4375 | G7: Broken-promise pattern: quote their last commitment back, require a dated schedule.
A8: 4 | B8: Vantage Media Group | C8: =AgingByCustomer!H5 -> 27300 | D8: =AgingByCustomer!I5 -> 19.650183 | E8: =C8*MAX(1,D8) -> 536450 | F8: =IFERROR(AVERAGEIFS(Data!$L$2:$L$251,Data!$B$2:$B$251,$B8,Data!$H$2:$H$251,"Paid*"),"n/a") -> 58.9 | G8: Chronic 55+ days: move to prepay or tightened terms at renewal; firm ladder on all open items now.
A9: 5 | B9: Foundry Dev Collective | C9: =AgingByCustomer!H4 -> 54100 | D9: =AgingByCustomer!I4 -> 7.6081331 | E9: =C9*MAX(1,D9) -> 411600 | F9: =IFERROR(AVERAGEIFS(Data!$L$2:$L$251,Data!$B$2:$B$251,$B9,Data!$H$2:$H$251,"Paid*"),"n/a") -> 9.7272727 | G9: Verify acceptance sign-off on milestones; isolate any disputed line and collect the clean balance.
A10: 6 | B10: Northgate Property Mgmt | C10: =AgingByCustomer!H11 -> 12800 | D10: =AgingByCustomer!I11 -> 25.929688 | E10: =C10*MAX(1,D10) -> 331900 | F10: =IFERROR(AVERAGEIFS(Data!$L$2:$L$251,Data!$B$2:$B$251,$B10,Data!$H$2:$H$251,"Paid*"),"n/a") -> 43.625 | G10: Fixed-cycle payer: align invoice submission to their run cutoff; chase the cycle, not the person.
A11: 7 | B11: Meridian Health Partners | C11: =AgingByCustomer!H7 -> 22000 | D11: =AgingByCustomer!I7 -> 3.1977273 | E11: =C11*MAX(1,D11) -> 70350 | F11: =IFERROR(AVERAGEIFS(Data!$L$2:$L$251,Data!$B$2:$B$251,$B11,Data!$H$2:$H$251,"Paid*"),"n/a") -> 14.714286 | G11: Trend +11 days and worsening: relationship call this week to find the cause before it compounds.
A12: 8 | B12: Cascade Logistics | C12: =AgingByCustomer!H6 -> 23450 | D12: =AgingByCustomer!I6 -> 0 | E12: =C12*MAX(1,D12) -> 23450 | F12: =IFERROR(AVERAGEIFS(Data!$L$2:$L$251,Data!$B$2:$B$251,$B12,Data!$H$2:$H$251,"Paid*"),"n/a") -> 9.4166667 | G12: Single large invoice: direct AP status call; likely approval-cycle issue, not refusal.
A13: 9 | B13: Stellar Staffing Co | C13: =AgingByCustomer!H9 -> 14400 | D13: =AgingByCustomer!I9 -> 0 | E13: =C13*MAX(1,D13) -> 14400 | F13: =IFERROR(AVERAGEIFS(Data!$L$2:$L$251,Data!$B$2:$B$251,$B13,Data!$H$2:$H$251,"Paid*"),"n/a") -> 3.2857143 | G13: Reliable: gentle nudge only; protect the relationship.
A14: 10 | B14: Quarry & Co Wholesale | C14: =AgingByCustomer!H10 -> 14300 | D14: =AgingByCustomer!I10 -> 0 | E14: =C14*MAX(1,D14) -> 14300 | F14: =IFERROR(AVERAGEIFS(Data!$L$2:$L$251,Data!$B$2:$B$251,$B14,Data!$H$2:$H$251,"Paid*"),"n/a") -> 25.277778 | G14: Standard ladder; consider order-hold trade if a new PO arrives before payment.
